AUTHORS
COPYING
MANIFEST.in
README
manual.pdf
setup.py
Surpriser.egg-info/PKG-INFO
Surpriser.egg-info/SOURCES.txt
Surpriser.egg-info/dependency_links.txt
Surpriser.egg-info/top_level.txt
Surpriser2/__init__.py
Surpriser2/benchmark.py
Surpriser2/data.py
Surpriser2/csources/_Surprise.c
Surpriser2/csources/_Uts.c
Surpriser2/csources/randoms.c
Surpriser2/csources/randoms.h
Surpriser2/csources/surprise.c
Surpriser2/csources/surprise.h
Surpriser2/data/243273.txt
Surpriser2/data/243273_prots.txt
Surpriser2/data/mets_syn.txt
Surpriser2/data/parts.dat
Surpriser2/data/syn.txt
Surpriser3/__init__.py
Surpriser3/benchmark.py
Surpriser3/data.py
Surpriser3/csources/_Surprise.c
Surpriser3/csources/_Uts.c
Surpriser3/csources/randoms.c
Surpriser3/csources/randoms.h
Surpriser3/csources/surprise.c
Surpriser3/csources/surprise.h
Surpriser3/data/243273.txt
Surpriser3/data/243273_prots.txt
Surpriser3/data/mets_syn.txt
Surpriser3/data/parts.dat
Surpriser3/data/syn.txt